pylint_robodk/__init__.py
pylint_robodk/pylint_robodk.py
robodk/__init__.py
robodk/roboapps.py
robodk/robodialogs.py
robodk/robofileio.py
robodk/robolink.py
robodk/robolinkutils.py
robodk/robomath.py
robolink/__init__.py
robodk-5.9.2.dist-info/LICENSE
robodk-5.9.2.dist-info/METADATA
robodk-5.9.2.dist-info/WHEEL
robodk-5.9.2.dist-info/top_level.txt
robodk-5.9.2.dist-info/RECORD
