Metadata-Version: 2.1
Name: robodk
Version: 5.9.2
Summary: RoboDK tools for simulating and programming industrial robots (implements the RoboDK API)
Home-page: https://robodk.com/doc/en/PythonAPI/index.html
Author: RoboDK Inc.
Author-email: info@robodk.com
License: Apache Software License
Keywords: industrial robot,simulation,offline programming,robot programming,robotics,online programming,3D simulator,post processors
Classifier: Development Status :: 5 - Production/Stable
Classifier: Intended Audience :: Manufacturing
Classifier: Intended Audience :: Education
Classifier: Intended Audience :: Information Technology
Classifier: Intended Audience :: Science/Research
Classifier: Intended Audience :: Developers
Classifier: Topic :: Software Development
Classifier: Topic :: Software Development :: Build Tools
Classifier: Topic :: Scientific/Engineering
Classifier: Topic :: Scientific/Engineering :: Visualization
Classifier: Topic :: Scientific/Engineering :: Mathematics
Classifier: Operating System :: MacOS :: MacOS X
Classifier: Operating System :: Microsoft :: Windows
Classifier: Operating System :: POSIX :: Linux
Classifier: Operating System :: OS Independent
Classifier: Framework :: Robot Framework
Classifier: Framework :: Robot Framework :: Library
Classifier: Framework :: Robot Framework :: Tool
Classifier: License :: OSI Approved :: Apache Software License
Classifier: Programming Language :: Python :: 3
Classifier: Programming Language :: Python :: 3.5
Classifier: Programming Language :: Python :: 3.6
Classifier: Programming Language :: Python :: 3.7
Classifier: Programming Language :: Python :: 3.8
Classifier: Programming Language :: Python :: 3.9
Classifier: Programming Language :: Python :: 3.10
Classifier: Programming Language :: Python :: 3.11
Classifier: Programming Language :: C
Classifier: Programming Language :: C#
Classifier: Programming Language :: C++
Classifier: Programming Language :: Visual Basic
Classifier: Typing :: Typed
Requires-Python: >=3.5
License-File: LICENSE
Provides-Extra: apps
Requires-Dist: PySide2 ==5.15.* ; extra == 'apps'
Provides-Extra: cv
Requires-Dist: opencv-contrib-python ; extra == 'cv'
Requires-Dist: numpy ; extra == 'cv'
Provides-Extra: lint
Requires-Dist: astroid ; extra == 'lint'
